{
    "image": "21892539--20240625--Pelvis0.jpg",
    "objects": [
        {
            "label": "LeftHip",
            "points": [
                [
                    483,
                    732
                ],
                [
                    813,
                    1133
                ]
            ]
        },
        {
            "label": "RightHip",
            "points": [
                [
                    1201,
                    669
                ],
                [
                    1662,
                    1060
                ]
            ]
        }
    ]
}