{
    "image": "22087567--20240124--Pelvis0.jpg",
    "objects": [
        {
            "label": "LeftHip",
            "points": [
                [
                    264,
                    451
                ],
                [
                    513,
                    783
                ]
            ]
        },
        {
            "label": "RightHip",
            "points": [
                [
                    811,
                    444
                ],
                [
                    1077,
                    770
                ]
            ]
        }
    ]
}