{
    "image": "22215179-060.jpg",
    "objects": [
        {
            "label": "LeftHip",
            "points": [
                [
                    926,
                    487
                ],
                [
                    1195,
                    918
                ]
            ]
        },
        {
            "label": "RightHip",
            "points": [
                [
                    1548,
                    499
                ],
                [
                    1817,
                    933
                ]
            ]
        }
    ]
}