{
    "image": "21855858--20230412--Pelvis0.jpg",
    "objects": [
        {
            "label": "LeftHip",
            "points": [
                [
                    372,
                    275
                ],
                [
                    605,
                    570
                ]
            ]
        },
        {
            "label": "RightHip",
            "points": [
                [
                    863,
                    248
                ],
                [
                    1105,
                    546
                ]
            ]
        }
    ]
}